sparql_file/__init__.py
sparql_file/cli.py
sparql_file/env.py
sparql_file-0.2.0.dist-info/METADATA
sparql_file-0.2.0.dist-info/WHEEL
sparql_file-0.2.0.dist-info/entry_points.txt
sparql_file-0.2.0.dist-info/RECORD
