Metadata-Version: 2.3
Name: sparql-file
Version: 0.2.0
Summary: A simple SPARQL 1.1 endpoint based on a file.
License: GPL-3.0-or-later
Author: Natanael Arndt
Author-email: arndtn@gmail.com
Requires-Python: >=3.9,<4.0.0
Classifier: License :: OSI Approved :: GNU General Public License v3 or later (GPLv3+)
Classifier: Programming Language :: Python :: 3
Classifier: Programming Language :: Python :: 3.9
Classifier: Programming Language :: Python :: 3.10
Classifier: Programming Language :: Python :: 3.11
Classifier: Programming Language :: Python :: 3.12
Classifier: Programming Language :: Python :: 3.13
Provides-Extra: cli
Requires-Dist: rdflib-endpoint (>=0.5.1,<0.6.0)
Requires-Dist: typer (>=0.16.1,<0.17.0) ; extra == "cli"
Requires-Dist: uvicorn (>=0.34.0,<0.35.0)
Project-URL: Bug Tracker, https://github.com/AKSW/sparql-file/issues
Project-URL: Homepage, https://github.com/AKSW/sparql-file
Project-URL: Repository, https://github.com/AKSW/sparql-file.git
